otsucfgmng/__init__.py
otsucfgmng/configuration_manager.py
otsucfgmng/funcs.py
otsucfgmng/protocol.py
otsucfgmng-1.4.0.312.dist-info/LICENSE.txt
otsucfgmng-1.4.0.312.dist-info/METADATA
otsucfgmng-1.4.0.312.dist-info/WHEEL
otsucfgmng-1.4.0.312.dist-info/top_level.txt
otsucfgmng-1.4.0.312.dist-info/RECORD
