Metadata-Version: 2.1
Name: otsucfgmng
Version: 1.4.0.312
Summary: 設定ファイルを扱うクラスを生成するライブラリです。
Home-page: https://github.com/Otsuhachi/OtsuConfigurationManager.git
Author: Otsuhachi
Author-email: agequodagis.tufuiegoeris@gmail.com
License: MIT License
Keywords: Python ConfigurationManager Configure json
Requires-Python: >=3.12
License-File: LICENSE.txt
Requires-Dist: otsuvalidator
Requires-Dist: otsutil
